sphinx_pushfeedback/__init__.py
sphinx_pushfeedback-0.1.8.dist-info/licenses/LICENSE.md
sphinx_pushfeedback-0.1.8.dist-info/WHEEL
sphinx_pushfeedback-0.1.8.dist-info/METADATA
sphinx_pushfeedback-0.1.8.dist-info/RECORD
