Metadata-Version: 2.4
Name: sphinx_pushfeedback
Version: 0.1.8
Summary: Feedback widget for Sphinx.
Home-page: https://github.com/techdocsstudio/sphinx-pushfeedback
Author: TechDocs Studio
Author-email: info@techdocs.studio
Requires-Python: >=3.7
Classifier: Framework :: Sphinx :: Extension
License-File: LICENSE.md
Requires-Dist: sphinx >= 3
Requires-Dist: furo ; extra == "doc"
Requires-Dist: pre-commit ; extra == "test"
Requires-Dist: pytest ; extra == "test"
Provides-Extra: doc
Provides-Extra: test
